MANIFEST.in
README.rst
setup.py
bin/django-fields
django_default_imagefield.egg-info/PKG-INFO
django_default_imagefield.egg-info/SOURCES.txt
django_default_imagefield.egg-info/dependency_links.txt
django_default_imagefield.egg-info/not-zip-safe
django_default_imagefield.egg-info/top_level.txt
django_fields/__init__.py
django_fields/admin.py
django_fields/apps.py
django_fields/fields.py
django_fields/models.py
django_fields/tests.py
django_fields/views.py