Metadata-Version: 1.1
Name: django-default-imagefield
Version: 0.5
Summary: Default static path for Django ImageField
Home-page: https://github.com/LeeHanYeong/Django-Default-ImageField
Author: Lee HanYeong
Author-email: dev@lhy.kr
License: MIT
Platform: UNKNOWN
Classifier: Framework :: Django
Classifier: Intended Audience :: Developers
Classifier: Programming Language :: Python
Classifier: Programming Language :: Python :: 3.6
